{
  "annotations": {
    "list": [
      {
        "builtIn": 1,
        "datasource": "-- Grafana --",
        "enable": true,
        "hide": true,
        "iconColor": "rgba(0, 211, 255, 1)",
        "name": "Annotations & Alerts",
        "type": "dashboard"
      }
    ]
  },
  "editable": true,
  "gnetId": null,
  "graphTooltip": 0,
  "id": 3,
  "iteration": 1584283299548,
  "links": [],
  "panels": [
    {
      "datasource": null,
      "gridPos": {
        "h": 1,
        "w": 24,
        "x": 0,
        "y": 0
      },
      "id": 45,
      "title": "Logs",
      "type": "row"
    },
    {
      "columns": [],
      "datasource": "InfluxDB",
      "fontSize": "100%",
      "gridPos": {
        "h": 11,
        "w": 24,
        "x": 0,
        "y": 1
      },
      "id": 67,
      "options": {},
      "pageSize": null,
      "repeat": null,
      "showHeader": true,
      "sort": {
        "col": 0,
        "desc": true
      },
      "styles": [
        {
          "alias": "Time",
          "align": "auto",
          "dateFormat": "YYYY-MM-DD HH:mm:ss",
          "link": false,
          "pattern": "Time",
          "type": "date"
        },
        {
          "alias": "",
          "align": "auto",
          "colorMode": null,
          "colors": [
            "rgba(245, 54, 54, 0.9)",
            "rgba(237, 129, 40, 0.89)",
            "rgba(50, 172, 45, 0.97)"
          ],
          "decimals": 2,
          "pattern": "/.*/",
          "thresholds": [],
          "type": "number",
          "unit": "short"
        }
      ],
      "targets": [
        {
          "groupBy": [
            {
              "params": [
                "$__interval"
              ],
              "type": "time"
            },
            {
              "params": [
                "null"
              ],
              "type": "fill"
            }
          ],
          "measurement": "logs",
          "orderByTime": "ASC",
          "policy": "default",
          "query": "SELECT mean(*) FROM \"logs\" WHERE $timeFilter GROUP BY time($__interval) fill(null)",
          "rawQuery": true,
          "refId": "A",
          "resultFormat": "table",
          "select": [
            [
              {
                "params": [
                  "*"
                ],
                "type": "field"
              },
              {
                "params": [],
                "type": "mean"
              }
            ]
          ],
          "tags": []
        }
      ],
      "timeFrom": null,
      "timeShift": null,
      "title": "Logs",
      "transform": "table",
      "type": "table"
    },
    {
      "collapsed": false,
      "datasource": null,
      "gridPos": {
        "h": 1,
        "w": 24,
        "x": 0,
        "y": 12
      },
      "id": 10,
      "panels": [],
      "repeat": "host",
      "scopedVars": {
        "host": {
          "selected": false,
          "text": "ubuntu-server",
          "value": "ubuntu-server"
        }
      },
      "title": "System Overview [[host]]",
      "type": "row"
    },
    {
      "alert": {
        "alertRuleTags": {},
        "conditions": [
          {
            "evaluator": {
              "params": [
                80
              ],
              "type": "gt"
            },
            "operator": {
              "type": "and"
            },
            "query": {
              "params": [
                "A",
                "5m",
                "now"
              ]
            },
            "reducer": {
              "params": [],
              "type": "avg"
            },
            "type": "query"
          }
        ],
        "executionErrorState": "alerting",
        "for": "5m",
        "frequency": "1m",
        "handler": 1,
        "name": "CPU - alert $host [host] [[host]]",
        "noDataState": "ok",
        "notifications": []
      },
      "aliasColors": {},
      "bars": false,
      "dashLength": 10,
      "dashes": false,
      "datasource": "InfluxDB",
      "fill": 1,
      "fillGradient": 0,
      "gridPos": {
        "h": 8,
        "w": 12,
        "x": 0,
        "y": 13
      },
      "hiddenSeries": false,
      "id": 8,
      "legend": {
        "alignAsTable": true,
        "avg": false,
        "current": false,
        "max": false,
        "min": false,
        "rightSide": true,
        "show": true,
        "total": false,
        "values": false
      },
      "lines": true,
      "linewidth": 1,
      "nullPointMode": "null as zero",
      "options": {
        "dataLinks": []
      },
      "percentage": false,
      "pointradius": 2,
      "points": false,
      "renderer": "flot",
      "repeat": null,
      "repeatDirection": "h",
      "scopedVars": {
        "host": {
          "selected": false,
          "text": "ubuntu-server",
          "value": "ubuntu-server"
        }
      },
      "seriesOverrides": [],
      "spaceLength": 10,
      "stack": false,
      "steppedLine": false,
      "targets": [
        {
          "groupBy": [
            {
              "params": [
                "$__interval"
              ],
              "type": "time"
            },
            {
              "params": [
                "null"
              ],
              "type": "fill"
            }
          ],
          "measurement": "cpu",
          "orderByTime": "ASC",
          "policy": "default",
          "query": "SELECT mean(*) FROM \"cpu\" WHERE (\"host\" =~ /$host/) AND $timeFilter GROUP BY time($__interval) fill(linear)",
          "rawQuery": true,
          "refId": "A",
          "resultFormat": "time_series",
          "select": [
            [
              {
                "params": [
                  "*"
                ],
                "type": "field"
              },
              {
                "params": [],
                "type": "mean"
              }
            ]
          ],
          "tags": [
            {
              "key": "host",
              "operator": "=",
              "value": "select tag value"
            }
          ]
        }
      ],
      "thresholds": [
        {
          "colorMode": "critical",
          "fill": true,
          "line": true,
          "op": "gt",
          "value": 80
        }
      ],
      "timeFrom": null,
      "timeRegions": [],
      "timeShift": null,
      "title": "CPU - [[host]]",
      "tooltip": {
        "shared": true,
        "sort": 2,
        "value_type": "individual"
      },
      "type": "graph",
      "xaxis": {
        "buckets": null,
        "mode": "time",
        "name": null,
        "show": true,
        "values": []
      },
      "yaxes": [
        {
          "format": "short",
          "label": null,
          "logBase": 1,
          "max": null,
          "min": null,
          "show": true
        },
        {
          "format": "short",
          "label": null,
          "logBase": 1,
          "max": null,
          "min": null,
          "show": true
        }
      ],
      "yaxis": {
        "align": false,
        "alignLevel": null
      }
    },
    {
      "alert": {
        "alertRuleTags": {},
        "conditions": [
          {
            "evaluator": {
              "params": [
                31461038961
              ],
              "type": "gt"
            },
            "operator": {
              "type": "and"
            },
            "query": {
              "params": [
                "A",
                "5m",
                "now"
              ]
            },
            "reducer": {
              "params": [],
              "type": "avg"
            },
            "type": "query"
          }
        ],
        "executionErrorState": "alerting",
        "for": "5m",
        "frequency": "1m",
        "handler": 1,
        "name": "Disk - host alert",
        "noDataState": "no_data",
        "notifications": []
      },
      "aliasColors": {},
      "bars": false,
      "dashLength": 10,
      "dashes": false,
      "datasource": null,
      "fill": 1,
      "fillGradient": 0,
      "gridPos": {
        "h": 8,
        "w": 12,
        "x": 12,
        "y": 13
      },
      "hiddenSeries": false,
      "id": 16,
      "legend": {
        "alignAsTable": true,
        "avg": false,
        "current": false,
        "max": false,
        "min": false,
        "rightSide": true,
        "show": true,
        "total": false,
        "values": false
      },
      "lines": true,
      "linewidth": 1,
      "nullPointMode": "null as zero",
      "options": {
        "dataLinks": []
      },
      "percentage": false,
      "pointradius": 2,
      "points": false,
      "renderer": "flot",
      "repeat": null,
      "scopedVars": {
        "host": {
          "selected": false,
          "text": "ubuntu-server",
          "value": "ubuntu-server"
        }
      },
      "seriesOverrides": [],
      "spaceLength": 10,
      "stack": false,
      "steppedLine": false,
      "targets": [
        {
          "groupBy": [
            {
              "params": [
                "$__interval"
              ],
              "type": "time"
            },
            {
              "params": [
                "null"
              ],
              "type": "fill"
            }
          ],
          "measurement": "disk",
          "orderByTime": "ASC",
          "policy": "default",
          "query": "SELECT mean(*) FROM \"disk\" WHERE (\"host\" =~ /$host/) AND $timeFilter GROUP BY time($__interval) fill(linear)",
          "rawQuery": true,
          "refId": "A",
          "resultFormat": "time_series",
          "select": [
            [
              {
                "params": [
                  "*"
                ],
                "type": "field"
              },
              {
                "params": [],
                "type": "mean"
              }
            ]
          ],
          "tags": [
            {
              "key": "host",
              "operator": "=",
              "value": "select tag value"
            }
          ]
        }
      ],
      "thresholds": [
        {
          "colorMode": "critical",
          "fill": true,
          "line": true,
          "op": "gt",
          "value": 31461038961
        }
      ],
      "timeFrom": null,
      "timeRegions": [],
      "timeShift": null,
      "title": "Disk - [[host]]",
      "tooltip": {
        "shared": true,
        "sort": 2,
        "value_type": "individual"
      },
      "type": "graph",
      "xaxis": {
        "buckets": null,
        "mode": "time",
        "name": null,
        "show": true,
        "values": []
      },
      "yaxes": [
        {
          "format": "short",
          "label": null,
          "logBase": 1,
          "max": null,
          "min": null,
          "show": true
        },
        {
          "format": "short",
          "label": null,
          "logBase": 1,
          "max": null,
          "min": null,
          "show": true
        }
      ],
      "yaxis": {
        "align": false,
        "alignLevel": null
      }
    },
    {
      "aliasColors": {},
      "bars": false,
      "dashLength": 10,
      "dashes": false,
      "datasource": "InfluxDB",
      "fill": 1,
      "fillGradient": 0,
      "gridPos": {
        "h": 8,
        "w": 12,
        "x": 0,
        "y": 21
      },
      "hiddenSeries": false,
      "id": 29,
      "legend": {
        "alignAsTable": true,
        "avg": false,
        "current": false,
        "max": false,
        "min": false,
        "rightSide": true,
        "show": true,
        "total": false,
        "values": false
      },
      "lines": true,
      "linewidth": 1,
      "nullPointMode": "null as zero",
      "options": {
        "dataLinks": []
      },
      "percentage": false,
      "pointradius": 2,
      "points": false,
      "renderer": "flot",
      "repeat": null,
      "scopedVars": {
        "host": {
          "selected": false,
          "text": "ubuntu-server",
          "value": "ubuntu-server"
        }
      },
      "seriesOverrides": [],
      "spaceLength": 10,
      "stack": false,
      "steppedLine": false,
      "targets": [
        {
          "groupBy": [
            {
              "params": [
                "$__interval"
              ],
              "type": "time"
            },
            {
              "params": [
                "null"
              ],
              "type": "fill"
            }
          ],
          "orderByTime": "ASC",
          "policy": "default",
          "query": "SELECT mean(*) FROM \"diskio\" WHERE (\"host\" =~ /$host/) AND $timeFilter GROUP BY time($__interval) fill(linear)",
          "rawQuery": true,
          "refId": "A",
          "resultFormat": "time_series",
          "select": [
            [
              {
                "params": [
                  "value"
                ],
                "type": "field"
              },
              {
                "params": [],
                "type": "mean"
              }
            ]
          ],
          "tags": []
        }
      ],
      "thresholds": [],
      "timeFrom": null,
      "timeRegions": [],
      "timeShift": null,
      "title": "DiskIO - [[host]]",
      "tooltip": {
        "shared": true,
        "sort": 2,
        "value_type": "individual"
      },
      "type": "graph",
      "xaxis": {
        "buckets": null,
        "mode": "time",
        "name": null,
        "show": true,
        "values": []
      },
      "yaxes": [
        {
          "format": "short",
          "label": null,
          "logBase": 1,
          "max": null,
          "min": null,
          "show": true
        },
        {
          "format": "short",
          "label": null,
          "logBase": 1,
          "max": null,
          "min": null,
          "show": true
        }
      ],
      "yaxis": {
        "align": false,
        "alignLevel": null
      }
    },
    {
      "aliasColors": {},
      "bars": false,
      "dashLength": 10,
      "dashes": false,
      "datasource": "InfluxDB",
      "fill": 1,
      "fillGradient": 0,
      "gridPos": {
        "h": 8,
        "w": 12,
        "x": 12,
        "y": 21
      },
      "hiddenSeries": false,
      "id": 30,
      "legend": {
        "alignAsTable": true,
        "avg": false,
        "current": false,
        "max": false,
        "min": false,
        "rightSide": true,
        "show": true,
        "total": false,
        "values": false
      },
      "lines": true,
      "linewidth": 1,
      "nullPointMode": "null as zero",
      "options": {
        "dataLinks": []
      },
      "percentage": false,
      "pointradius": 2,
      "points": false,
      "renderer": "flot",
      "repeat": null,
      "scopedVars": {
        "host": {
          "selected": false,
          "text": "ubuntu-server",
          "value": "ubuntu-server"
        }
      },
      "seriesOverrides": [],
      "spaceLength": 10,
      "stack": false,
      "steppedLine": false,
      "targets": [
        {
          "groupBy": [
            {
              "params": [
                "$__interval"
              ],
              "type": "time"
            },
            {
              "params": [
                "null"
              ],
              "type": "fill"
            }
          ],
          "orderByTime": "ASC",
          "policy": "default",
          "query": "SELECT mean(*) FROM \"kernel\" WHERE (\"host\" =~ /$host/) AND $timeFilter GROUP BY time($__interval) fill(linear)",
          "rawQuery": true,
          "refId": "A",
          "resultFormat": "time_series",
          "select": [
            [
              {
                "params": [
                  "value"
                ],
                "type": "field"
              },
              {
                "params": [],
                "type": "mean"
              }
            ]
          ],
          "tags": []
        }
      ],
      "thresholds": [],
      "timeFrom": null,
      "timeRegions": [],
      "timeShift": null,
      "title": "Kernel - [[host]]",
      "tooltip": {
        "shared": true,
        "sort": 2,
        "value_type": "individual"
      },
      "type": "graph",
      "xaxis": {
        "buckets": null,
        "mode": "time",
        "name": null,
        "show": true,
        "values": []
      },
      "yaxes": [
        {
          "format": "short",
          "label": null,
          "logBase": 1,
          "max": null,
          "min": null,
          "show": true
        },
        {
          "format": "short",
          "label": null,
          "logBase": 1,
          "max": null,
          "min": null,
          "show": true
        }
      ],
      "yaxis": {
        "align": false,
        "alignLevel": null
      }
    },
    {
      "aliasColors": {},
      "bars": false,
      "dashLength": 10,
      "dashes": false,
      "datasource": "InfluxDB",
      "fill": 1,
      "fillGradient": 0,
      "gridPos": {
        "h": 8,
        "w": 12,
        "x": 0,
        "y": 29
      },
      "hiddenSeries": false,
      "id": 31,
      "legend": {
        "alignAsTable": true,
        "avg": false,
        "current": false,
        "max": false,
        "min": false,
        "rightSide": true,
        "show": true,
        "total": false,
        "values": false
      },
      "lines": true,
      "linewidth": 1,
      "nullPointMode": "null as zero",
      "options": {
        "dataLinks": []
      },
      "percentage": false,
      "pointradius": 2,
      "points": false,
      "renderer": "flot",
      "repeat": null,
      "scopedVars": {
        "host": {
          "selected": false,
          "text": "ubuntu-server",
          "value": "ubuntu-server"
        }
      },
      "seriesOverrides": [],
      "spaceLength": 10,
      "stack": false,
      "steppedLine": false,
      "targets": [
        {
          "groupBy": [
            {
              "params": [
                "$__interval"
              ],
              "type": "time"
            },
            {
              "params": [
                "null"
              ],
              "type": "fill"
            }
          ],
          "orderByTime": "ASC",
          "policy": "default",
          "query": "SELECT mean(*) FROM \"mem\" WHERE (\"host\" =~ /$host/) AND $timeFilter GROUP BY time($__interval) fill(linear)",
          "rawQuery": true,
          "refId": "A",
          "resultFormat": "time_series",
          "select": [
            [
              {
                "params": [
                  "value"
                ],
                "type": "field"
              },
              {
                "params": [],
                "type": "mean"
              }
            ]
          ],
          "tags": []
        }
      ],
      "thresholds": [],
      "timeFrom": null,
      "timeRegions": [],
      "timeShift": null,
      "title": "Memory - [[host]]",
      "tooltip": {
        "shared": true,
        "sort": 2,
        "value_type": "individual"
      },
      "type": "graph",
      "xaxis": {
        "buckets": null,
        "mode": "time",
        "name": null,
        "show": true,
        "values": []
      },
      "yaxes": [
        {
          "format": "short",
          "label": null,
          "logBase": 1,
          "max": null,
          "min": null,
          "show": true
        },
        {
          "format": "short",
          "label": null,
          "logBase": 1,
          "max": null,
          "min": null,
          "show": true
        }
      ],
      "yaxis": {
        "align": false,
        "alignLevel": null
      }
    },
    {
      "aliasColors": {},
      "bars": false,
      "dashLength": 10,
      "dashes": false,
      "datasource": "InfluxDB",
      "fill": 1,
      "fillGradient": 0,
      "gridPos": {
        "h": 8,
        "w": 12,
        "x": 12,
        "y": 29
      },
      "hiddenSeries": false,
      "id": 32,
      "legend": {
        "alignAsTable": true,
        "avg": false,
        "current": false,
        "max": false,
        "min": false,
        "rightSide": true,
        "show": true,
        "total": false,
        "values": false
      },
      "lines": true,
      "linewidth": 1,
      "nullPointMode": "null as zero",
      "options": {
        "dataLinks": []
      },
      "percentage": false,
      "pointradius": 2,
      "points": false,
      "renderer": "flot",
      "repeat": null,
      "scopedVars": {
        "host": {
          "selected": false,
          "text": "ubuntu-server",
          "value": "ubuntu-server"
        }
      },
      "seriesOverrides": [],
      "spaceLength": 10,
      "stack": false,
      "steppedLine": false,
      "targets": [
        {
          "groupBy": [
            {
              "params": [
                "$__interval"
              ],
              "type": "time"
            },
            {
              "params": [
                "null"
              ],
              "type": "fill"
            }
          ],
          "orderByTime": "ASC",
          "policy": "default",
          "query": "SELECT mean(*) FROM \"processes\" WHERE (\"host\" =~ /$host/) AND $timeFilter GROUP BY time($__interval) fill(linear)",
          "rawQuery": true,
          "refId": "A",
          "resultFormat": "time_series",
          "select": [
            [
              {
                "params": [
                  "value"
                ],
                "type": "field"
              },
              {
                "params": [],
                "type": "mean"
              }
            ]
          ],
          "tags": []
        }
      ],
      "thresholds": [],
      "timeFrom": null,
      "timeRegions": [],
      "timeShift": null,
      "title": "Processes - [[host]]",
      "tooltip": {
        "shared": true,
        "sort": 2,
        "value_type": "individual"
      },
      "type": "graph",
      "xaxis": {
        "buckets": null,
        "mode": "time",
        "name": null,
        "show": true,
        "values": []
      },
      "yaxes": [
        {
          "format": "short",
          "label": null,
          "logBase": 1,
          "max": null,
          "min": null,
          "show": true
        },
        {
          "format": "short",
          "label": null,
          "logBase": 1,
          "max": null,
          "min": null,
          "show": true
        }
      ],
      "yaxis": {
        "align": false,
        "alignLevel": null
      }
    },
    {
      "aliasColors": {},
      "bars": false,
      "dashLength": 10,
      "dashes": false,
      "datasource": "InfluxDB",
      "fill": 1,
      "fillGradient": 0,
      "gridPos": {
        "h": 8,
        "w": 12,
        "x": 0,
        "y": 37
      },
      "hiddenSeries": false,
      "id": 33,
      "legend": {
        "alignAsTable": true,
        "avg": false,
        "current": false,
        "max": false,
        "min": false,
        "rightSide": true,
        "show": true,
        "total": false,
        "values": false
      },
      "lines": true,
      "linewidth": 1,
      "nullPointMode": "null as zero",
      "options": {
        "dataLinks": []
      },
      "percentage": false,
      "pointradius": 2,
      "points": false,
      "renderer": "flot",
      "repeat": null,
      "scopedVars": {
        "host": {
          "selected": false,
          "text": "ubuntu-server",
          "value": "ubuntu-server"
        }
      },
      "seriesOverrides": [],
      "spaceLength": 10,
      "stack": false,
      "steppedLine": false,
      "targets": [
        {
          "groupBy": [
            {
              "params": [
                "$__interval"
              ],
              "type": "time"
            },
            {
              "params": [
                "null"
              ],
              "type": "fill"
            }
          ],
          "orderByTime": "ASC",
          "policy": "default",
          "query": "SELECT mean(*) FROM \"netstat\" WHERE (\"host\" =~ /$host/) AND $timeFilter GROUP BY time($__interval) fill(linear)",
          "rawQuery": true,
          "refId": "A",
          "resultFormat": "time_series",
          "select": [
            [
              {
                "params": [
                  "value"
                ],
                "type": "field"
              },
              {
                "params": [],
                "type": "mean"
              }
            ]
          ],
          "tags": []
        }
      ],
      "thresholds": [],
      "timeFrom": null,
      "timeRegions": [],
      "timeShift": null,
      "title": "TCP connections - [[host]]",
      "tooltip": {
        "shared": true,
        "sort": 2,
        "value_type": "individual"
      },
      "type": "graph",
      "xaxis": {
        "buckets": null,
        "mode": "time",
        "name": null,
        "show": true,
        "values": []
      },
      "yaxes": [
        {
          "format": "short",
          "label": null,
          "logBase": 1,
          "max": null,
          "min": null,
          "show": true
        },
        {
          "format": "short",
          "label": null,
          "logBase": 1,
          "max": null,
          "min": null,
          "show": true
        }
      ],
      "yaxis": {
        "align": false,
        "alignLevel": null
      }
    },
    {
      "aliasColors": {},
      "bars": false,
      "dashLength": 10,
      "dashes": false,
      "datasource": "InfluxDB",
      "fill": 1,
      "fillGradient": 0,
      "gridPos": {
        "h": 8,
        "w": 12,
        "x": 12,
        "y": 37
      },
      "hiddenSeries": false,
      "id": 34,
      "legend": {
        "alignAsTable": true,
        "avg": false,
        "current": false,
        "max": false,
        "min": false,
        "rightSide": true,
        "show": true,
        "total": false,
        "values": false
      },
      "lines": true,
      "linewidth": 1,
      "nullPointMode": "null as zero",
      "options": {
        "dataLinks": []
      },
      "percentage": false,
      "pointradius": 2,
      "points": false,
      "renderer": "flot",
      "repeat": null,
      "scopedVars": {
        "host": {
          "selected": false,
          "text": "ubuntu-server",
          "value": "ubuntu-server"
        }
      },
      "seriesOverrides": [],
      "spaceLength": 10,
      "stack": false,
      "steppedLine": false,
      "targets": [
        {
          "groupBy": [
            {
              "params": [
                "$__interval"
              ],
              "type": "time"
            },
            {
              "params": [
                "null"
              ],
              "type": "fill"
            }
          ],
          "orderByTime": "ASC",
          "policy": "default",
          "query": "SELECT mean(*) FROM \"system\" WHERE (\"host\" =~ /$host/) AND $timeFilter GROUP BY time($__interval) fill(linear)",
          "rawQuery": true,
          "refId": "A",
          "resultFormat": "time_series",
          "select": [
            [
              {
                "params": [
                  "value"
                ],
                "type": "field"
              },
              {
                "params": [],
                "type": "mean"
              }
            ]
          ],
          "tags": []
        }
      ],
      "thresholds": [],
      "timeFrom": null,
      "timeRegions": [],
      "timeShift": null,
      "title": "System - [[host]]",
      "tooltip": {
        "shared": true,
        "sort": 2,
        "value_type": "individual"
      },
      "type": "graph",
      "xaxis": {
        "buckets": null,
        "mode": "time",
        "name": null,
        "show": true,
        "values": []
      },
      "yaxes": [
        {
          "format": "short",
          "label": null,
          "logBase": 1,
          "max": null,
          "min": null,
          "show": true
        },
        {
          "format": "short",
          "label": null,
          "logBase": 1,
          "max": null,
          "min": null,
          "show": true
        }
      ],
      "yaxis": {
        "align": false,
        "alignLevel": null
      }
    },
    {
      "collapsed": false,
      "datasource": null,
      "gridPos": {
        "h": 1,
        "w": 24,
        "x": 0,
        "y": 45
      },
      "id": 68,
      "panels": [],
      "repeat": null,
      "repeatIteration": 1584283299548,
      "repeatPanelId": 10,
      "scopedVars": {
        "host": {
          "selected": false,
          "text": "ubuntu-vm-test",
          "value": "ubuntu-vm-test"
        }
      },
      "title": "System Overview [[host]]",
      "type": "row"
    },
    {
      "alert": {
        "alertRuleTags": {},
        "conditions": [
          {
            "evaluator": {
              "params": [
                80
              ],
              "type": "gt"
            },
            "operator": {
              "type": "and"
            },
            "query": {
              "params": [
                "A",
                "5m",
                "now"
              ]
            },
            "reducer": {
              "params": [],
              "type": "avg"
            },
            "type": "query"
          }
        ],
        "executionErrorState": "alerting",
        "for": "5m",
        "frequency": "1m",
        "handler": 1,
        "name": "CPU - alert $host [host] [[host]]",
        "noDataState": "ok",
        "notifications": []
      },
      "aliasColors": {},
      "bars": false,
      "dashLength": 10,
      "dashes": false,
      "datasource": "InfluxDB",
      "fill": 1,
      "fillGradient": 0,
      "gridPos": {
        "h": 8,
        "w": 12,
        "x": 0,
        "y": 46
      },
      "hiddenSeries": false,
      "id": 69,
      "legend": {
        "alignAsTable": true,
        "avg": false,
        "current": false,
        "max": false,
        "min": false,
        "rightSide": true,
        "show": true,
        "total": false,
        "values": false
      },
      "lines": true,
      "linewidth": 1,
      "nullPointMode": "null as zero",
      "options": {
        "dataLinks": []
      },
      "percentage": false,
      "pointradius": 2,
      "points": false,
      "renderer": "flot",
      "repeat": null,
      "repeatDirection": "h",
      "repeatIteration": 1584283299548,
      "repeatPanelId": 8,
      "repeatedByRow": true,
      "scopedVars": {
        "host": {
          "selected": false,
          "text": "ubuntu-vm-test",
          "value": "ubuntu-vm-test"
        }
      },
      "seriesOverrides": [],
      "spaceLength": 10,
      "stack": false,
      "steppedLine": false,
      "targets": [
        {
          "groupBy": [
            {
              "params": [
                "$__interval"
              ],
              "type": "time"
            },
            {
              "params": [
                "null"
              ],
              "type": "fill"
            }
          ],
          "measurement": "cpu",
          "orderByTime": "ASC",
          "policy": "default",
          "query": "SELECT mean(*) FROM \"cpu\" WHERE (\"host\" =~ /$host/) AND $timeFilter GROUP BY time($__interval) fill(linear)",
          "rawQuery": true,
          "refId": "A",
          "resultFormat": "time_series",
          "select": [
            [
              {
                "params": [
                  "*"
                ],
                "type": "field"
              },
              {
                "params": [],
                "type": "mean"
              }
            ]
          ],
          "tags": [
            {
              "key": "host",
              "operator": "=",
              "value": "select tag value"
            }
          ]
        }
      ],
      "thresholds": [
        {
          "colorMode": "critical",
          "fill": true,
          "line": true,
          "op": "gt",
          "value": 80
        }
      ],
      "timeFrom": null,
      "timeRegions": [],
      "timeShift": null,
      "title": "CPU - [[host]]",
      "tooltip": {
        "shared": true,
        "sort": 2,
        "value_type": "individual"
      },
      "type": "graph",
      "xaxis": {
        "buckets": null,
        "mode": "time",
        "name": null,
        "show": true,
        "values": []
      },
      "yaxes": [
        {
          "format": "short",
          "label": null,
          "logBase": 1,
          "max": null,
          "min": null,
          "show": true
        },
        {
          "format": "short",
          "label": null,
          "logBase": 1,
          "max": null,
          "min": null,
          "show": true
        }
      ],
      "yaxis": {
        "align": false,
        "alignLevel": null
      }
    },
    {
      "alert": {
        "alertRuleTags": {},
        "conditions": [
          {
            "evaluator": {
              "params": [
                31461038961
              ],
              "type": "gt"
            },
            "operator": {
              "type": "and"
            },
            "query": {
              "params": [
                "A",
                "5m",
                "now"
              ]
            },
            "reducer": {
              "params": [],
              "type": "avg"
            },
            "type": "query"
          }
        ],
        "executionErrorState": "alerting",
        "for": "5m",
        "frequency": "1m",
        "handler": 1,
        "name": "Disk - host alert",
        "noDataState": "no_data",
        "notifications": []
      },
      "aliasColors": {},
      "bars": false,
      "dashLength": 10,
      "dashes": false,
      "datasource": null,
      "fill": 1,
      "fillGradient": 0,
      "gridPos": {
        "h": 8,
        "w": 12,
        "x": 12,
        "y": 46
      },
      "hiddenSeries": false,
      "id": 70,
      "legend": {
        "alignAsTable": true,
        "avg": false,
        "current": false,
        "max": false,
        "min": false,
        "rightSide": true,
        "show": true,
        "total": false,
        "values": false
      },
      "lines": true,
      "linewidth": 1,
      "nullPointMode": "null as zero",
      "options": {
        "dataLinks": []
      },
      "percentage": false,
      "pointradius": 2,
      "points": false,
      "renderer": "flot",
      "repeat": null,
      "repeatIteration": 1584283299548,
      "repeatPanelId": 16,
      "repeatedByRow": true,
      "scopedVars": {
        "host": {
          "selected": false,
          "text": "ubuntu-vm-test",
          "value": "ubuntu-vm-test"
        }
      },
      "seriesOverrides": [],
      "spaceLength": 10,
      "stack": false,
      "steppedLine": false,
      "targets": [
        {
          "groupBy": [
            {
              "params": [
                "$__interval"
              ],
              "type": "time"
            },
            {
              "params": [
                "null"
              ],
              "type": "fill"
            }
          ],
          "measurement": "disk",
          "orderByTime": "ASC",
          "policy": "default",
          "query": "SELECT mean(*) FROM \"disk\" WHERE (\"host\" =~ /$host/) AND $timeFilter GROUP BY time($__interval) fill(linear)",
          "rawQuery": true,
          "refId": "A",
          "resultFormat": "time_series",
          "select": [
            [
              {
                "params": [
                  "*"
                ],
                "type": "field"
              },
              {
                "params": [],
                "type": "mean"
              }
            ]
          ],
          "tags": [
            {
              "key": "host",
              "operator": "=",
              "value": "select tag value"
            }
          ]
        }
      ],
      "thresholds": [
        {
          "colorMode": "critical",
          "fill": true,
          "line": true,
          "op": "gt",
          "value": 31461038961
        }
      ],
      "timeFrom": null,
      "timeRegions": [],
      "timeShift": null,
      "title": "Disk - [[host]]",
      "tooltip": {
        "shared": true,
        "sort": 2,
        "value_type": "individual"
      },
      "type": "graph",
      "xaxis": {
        "buckets": null,
        "mode": "time",
        "name": null,
        "show": true,
        "values": []
      },
      "yaxes": [
        {
          "format": "short",
          "label": null,
          "logBase": 1,
          "max": null,
          "min": null,
          "show": true
        },
        {
          "format": "short",
          "label": null,
          "logBase": 1,
          "max": null,
          "min": null,
          "show": true
        }
      ],
      "yaxis": {
        "align": false,
        "alignLevel": null
      }
    },
    {
      "aliasColors": {},
      "bars": false,
      "dashLength": 10,
      "dashes": false,
      "datasource": "InfluxDB",
      "fill": 1,
      "fillGradient": 0,
      "gridPos": {
        "h": 8,
        "w": 12,
        "x": 0,
        "y": 54
      },
      "hiddenSeries": false,
      "id": 71,
      "legend": {
        "alignAsTable": true,
        "avg": false,
        "current": false,
        "max": false,
        "min": false,
        "rightSide": true,
        "show": true,
        "total": false,
        "values": false
      },
      "lines": true,
      "linewidth": 1,
      "nullPointMode": "null as zero",
      "options": {
        "dataLinks": []
      },
      "percentage": false,
      "pointradius": 2,
      "points": false,
      "renderer": "flot",
      "repeat": null,
      "repeatIteration": 1584283299548,
      "repeatPanelId": 29,
      "repeatedByRow": true,
      "scopedVars": {
        "host": {
          "selected": false,
          "text": "ubuntu-vm-test",
          "value": "ubuntu-vm-test"
        }
      },
      "seriesOverrides": [],
      "spaceLength": 10,
      "stack": false,
      "steppedLine": false,
      "targets": [
        {
          "groupBy": [
            {
              "params": [
                "$__interval"
              ],
              "type": "time"
            },
            {
              "params": [
                "null"
              ],
              "type": "fill"
            }
          ],
          "orderByTime": "ASC",
          "policy": "default",
          "query": "SELECT mean(*) FROM \"diskio\" WHERE (\"host\" =~ /$host/) AND $timeFilter GROUP BY time($__interval) fill(linear)",
          "rawQuery": true,
          "refId": "A",
          "resultFormat": "time_series",
          "select": [
            [
              {
                "params": [
                  "value"
                ],
                "type": "field"
              },
              {
                "params": [],
                "type": "mean"
              }
            ]
          ],
          "tags": []
        }
      ],
      "thresholds": [],
      "timeFrom": null,
      "timeRegions": [],
      "timeShift": null,
      "title": "DiskIO - [[host]]",
      "tooltip": {
        "shared": true,
        "sort": 2,
        "value_type": "individual"
      },
      "type": "graph",
      "xaxis": {
        "buckets": null,
        "mode": "time",
        "name": null,
        "show": true,
        "values": []
      },
      "yaxes": [
        {
          "format": "short",
          "label": null,
          "logBase": 1,
          "max": null,
          "min": null,
          "show": true
        },
        {
          "format": "short",
          "label": null,
          "logBase": 1,
          "max": null,
          "min": null,
          "show": true
        }
      ],
      "yaxis": {
        "align": false,
        "alignLevel": null
      }
    },
    {
      "aliasColors": {},
      "bars": false,
      "dashLength": 10,
      "dashes": false,
      "datasource": "InfluxDB",
      "fill": 1,
      "fillGradient": 0,
      "gridPos": {
        "h": 8,
        "w": 12,
        "x": 12,
        "y": 54
      },
      "hiddenSeries": false,
      "id": 72,
      "legend": {
        "alignAsTable": true,
        "avg": false,
        "current": false,
        "max": false,
        "min": false,
        "rightSide": true,
        "show": true,
        "total": false,
        "values": false
      },
      "lines": true,
      "linewidth": 1,
      "nullPointMode": "null as zero",
      "options": {
        "dataLinks": []
      },
      "percentage": false,
      "pointradius": 2,
      "points": false,
      "renderer": "flot",
      "repeat": null,
      "repeatIteration": 1584283299548,
      "repeatPanelId": 30,
      "repeatedByRow": true,
      "scopedVars": {
        "host": {
          "selected": false,
          "text": "ubuntu-vm-test",
          "value": "ubuntu-vm-test"
        }
      },
      "seriesOverrides": [],
      "spaceLength": 10,
      "stack": false,
      "steppedLine": false,
      "targets": [
        {
          "groupBy": [
            {
              "params": [
                "$__interval"
              ],
              "type": "time"
            },
            {
              "params": [
                "null"
              ],
              "type": "fill"
            }
          ],
          "orderByTime": "ASC",
          "policy": "default",
          "query": "SELECT mean(*) FROM \"kernel\" WHERE (\"host\" =~ /$host/) AND $timeFilter GROUP BY time($__interval) fill(linear)",
          "rawQuery": true,
          "refId": "A",
          "resultFormat": "time_series",
          "select": [
            [
              {
                "params": [
                  "value"
                ],
                "type": "field"
              },
              {
                "params": [],
                "type": "mean"
              }
            ]
          ],
          "tags": []
        }
      ],
      "thresholds": [],
      "timeFrom": null,
      "timeRegions": [],
      "timeShift": null,
      "title": "Kernel - [[host]]",
      "tooltip": {
        "shared": true,
        "sort": 2,
        "value_type": "individual"
      },
      "type": "graph",
      "xaxis": {
        "buckets": null,
        "mode": "time",
        "name": null,
        "show": true,
        "values": []
      },
      "yaxes": [
        {
          "format": "short",
          "label": null,
          "logBase": 1,
          "max": null,
          "min": null,
          "show": true
        },
        {
          "format": "short",
          "label": null,
          "logBase": 1,
          "max": null,
          "min": null,
          "show": true
        }
      ],
      "yaxis": {
        "align": false,
        "alignLevel": null
      }
    },
    {
      "aliasColors": {},
      "bars": false,
      "dashLength": 10,
      "dashes": false,
      "datasource": "InfluxDB",
      "fill": 1,
      "fillGradient": 0,
      "gridPos": {
        "h": 8,
        "w": 12,
        "x": 0,
        "y": 62
      },
      "hiddenSeries": false,
      "id": 73,
      "legend": {
        "alignAsTable": true,
        "avg": false,
        "current": false,
        "max": false,
        "min": false,
        "rightSide": true,
        "show": true,
        "total": false,
        "values": false
      },
      "lines": true,
      "linewidth": 1,
      "nullPointMode": "null as zero",
      "options": {
        "dataLinks": []
      },
      "percentage": false,
      "pointradius": 2,
      "points": false,
      "renderer": "flot",
      "repeat": null,
      "repeatIteration": 1584283299548,
      "repeatPanelId": 31,
      "repeatedByRow": true,
      "scopedVars": {
        "host": {
          "selected": false,
          "text": "ubuntu-vm-test",
          "value": "ubuntu-vm-test"
        }
      },
      "seriesOverrides": [],
      "spaceLength": 10,
      "stack": false,
      "steppedLine": false,
      "targets": [
        {
          "groupBy": [
            {
              "params": [
                "$__interval"
              ],
              "type": "time"
            },
            {
              "params": [
                "null"
              ],
              "type": "fill"
            }
          ],
          "orderByTime": "ASC",
          "policy": "default",
          "query": "SELECT mean(*) FROM \"mem\" WHERE (\"host\" =~ /$host/) AND $timeFilter GROUP BY time($__interval) fill(linear)",
          "rawQuery": true,
          "refId": "A",
          "resultFormat": "time_series",
          "select": [
            [
              {
                "params": [
                  "value"
                ],
                "type": "field"
              },
              {
                "params": [],
                "type": "mean"
              }
            ]
          ],
          "tags": []
        }
      ],
      "thresholds": [],
      "timeFrom": null,
      "timeRegions": [],
      "timeShift": null,
      "title": "Memory - [[host]]",
      "tooltip": {
        "shared": true,
        "sort": 2,
        "value_type": "individual"
      },
      "type": "graph",
      "xaxis": {
        "buckets": null,
        "mode": "time",
        "name": null,
        "show": true,
        "values": []
      },
      "yaxes": [
        {
          "format": "short",
          "label": null,
          "logBase": 1,
          "max": null,
          "min": null,
          "show": true
        },
        {
          "format": "short",
          "label": null,
          "logBase": 1,
          "max": null,
          "min": null,
          "show": true
        }
      ],
      "yaxis": {
        "align": false,
        "alignLevel": null
      }
    },
    {
      "aliasColors": {},
      "bars": false,
      "dashLength": 10,
      "dashes": false,
      "datasource": "InfluxDB",
      "fill": 1,
      "fillGradient": 0,
      "gridPos": {
        "h": 8,
        "w": 12,
        "x": 12,
        "y": 62
      },
      "hiddenSeries": false,
      "id": 74,
      "legend": {
        "alignAsTable": true,
        "avg": false,
        "current": false,
        "max": false,
        "min": false,
        "rightSide": true,
        "show": true,
        "total": false,
        "values": false
      },
      "lines": true,
      "linewidth": 1,
      "nullPointMode": "null as zero",
      "options": {
        "dataLinks": []
      },
      "percentage": false,
      "pointradius": 2,
      "points": false,
      "renderer": "flot",
      "repeat": null,
      "repeatIteration": 1584283299548,
      "repeatPanelId": 32,
      "repeatedByRow": true,
      "scopedVars": {
        "host": {
          "selected": false,
          "text": "ubuntu-vm-test",
          "value": "ubuntu-vm-test"
        }
      },
      "seriesOverrides": [],
      "spaceLength": 10,
      "stack": false,
      "steppedLine": false,
      "targets": [
        {
          "groupBy": [
            {
              "params": [
                "$__interval"
              ],
              "type": "time"
            },
            {
              "params": [
                "null"
              ],
              "type": "fill"
            }
          ],
          "orderByTime": "ASC",
          "policy": "default",
          "query": "SELECT mean(*) FROM \"processes\" WHERE (\"host\" =~ /$host/) AND $timeFilter GROUP BY time($__interval) fill(linear)",
          "rawQuery": true,
          "refId": "A",
          "resultFormat": "time_series",
          "select": [
            [
              {
                "params": [
                  "value"
                ],
                "type": "field"
              },
              {
                "params": [],
                "type": "mean"
              }
            ]
          ],
          "tags": []
        }
      ],
      "thresholds": [],
      "timeFrom": null,
      "timeRegions": [],
      "timeShift": null,
      "title": "Processes - [[host]]",
      "tooltip": {
        "shared": true,
        "sort": 2,
        "value_type": "individual"
      },
      "type": "graph",
      "xaxis": {
        "buckets": null,
        "mode": "time",
        "name": null,
        "show": true,
        "values": []
      },
      "yaxes": [
        {
          "format": "short",
          "label": null,
          "logBase": 1,
          "max": null,
          "min": null,
          "show": true
        },
        {
          "format": "short",
          "label": null,
          "logBase": 1,
          "max": null,
          "min": null,
          "show": true
        }
      ],
      "yaxis": {
        "align": false,
        "alignLevel": null
      }
    },
    {
      "aliasColors": {},
      "bars": false,
      "dashLength": 10,
      "dashes": false,
      "datasource": "InfluxDB",
      "fill": 1,
      "fillGradient": 0,
      "gridPos": {
        "h": 8,
        "w": 12,
        "x": 0,
        "y": 70
      },
      "hiddenSeries": false,
      "id": 75,
      "legend": {
        "alignAsTable": true,
        "avg": false,
        "current": false,
        "max": false,
        "min": false,
        "rightSide": true,
        "show": true,
        "total": false,
        "values": false
      },
      "lines": true,
      "linewidth": 1,
      "nullPointMode": "null as zero",
      "options": {
        "dataLinks": []
      },
      "percentage": false,
      "pointradius": 2,
      "points": false,
      "renderer": "flot",
      "repeat": null,
      "repeatIteration": 1584283299548,
      "repeatPanelId": 33,
      "repeatedByRow": true,
      "scopedVars": {
        "host": {
          "selected": false,
          "text": "ubuntu-vm-test",
          "value": "ubuntu-vm-test"
        }
      },
      "seriesOverrides": [],
      "spaceLength": 10,
      "stack": false,
      "steppedLine": false,
      "targets": [
        {
          "groupBy": [
            {
              "params": [
                "$__interval"
              ],
              "type": "time"
            },
            {
              "params": [
                "null"
              ],
              "type": "fill"
            }
          ],
          "orderByTime": "ASC",
          "policy": "default",
          "query": "SELECT mean(*) FROM \"netstat\" WHERE (\"host\" =~ /$host/) AND $timeFilter GROUP BY time($__interval) fill(linear)",
          "rawQuery": true,
          "refId": "A",
          "resultFormat": "time_series",
          "select": [
            [
              {
                "params": [
                  "value"
                ],
                "type": "field"
              },
              {
                "params": [],
                "type": "mean"
              }
            ]
          ],
          "tags": []
        }
      ],
      "thresholds": [],
      "timeFrom": null,
      "timeRegions": [],
      "timeShift": null,
      "title": "TCP connections - [[host]]",
      "tooltip": {
        "shared": true,
        "sort": 2,
        "value_type": "individual"
      },
      "type": "graph",
      "xaxis": {
        "buckets": null,
        "mode": "time",
        "name": null,
        "show": true,
        "values": []
      },
      "yaxes": [
        {
          "format": "short",
          "label": null,
          "logBase": 1,
          "max": null,
          "min": null,
          "show": true
        },
        {
          "format": "short",
          "label": null,
          "logBase": 1,
          "max": null,
          "min": null,
          "show": true
        }
      ],
      "yaxis": {
        "align": false,
        "alignLevel": null
      }
    },
    {
      "aliasColors": {},
      "bars": false,
      "dashLength": 10,
      "dashes": false,
      "datasource": "InfluxDB",
      "fill": 1,
      "fillGradient": 0,
      "gridPos": {
        "h": 8,
        "w": 12,
        "x": 12,
        "y": 70
      },
      "hiddenSeries": false,
      "id": 76,
      "legend": {
        "alignAsTable": true,
        "avg": false,
        "current": false,
        "max": false,
        "min": false,
        "rightSide": true,
        "show": true,
        "total": false,
        "values": false
      },
      "lines": true,
      "linewidth": 1,
      "nullPointMode": "null as zero",
      "options": {
        "dataLinks": []
      },
      "percentage": false,
      "pointradius": 2,
      "points": false,
      "renderer": "flot",
      "repeat": null,
      "repeatIteration": 1584283299548,
      "repeatPanelId": 34,
      "repeatedByRow": true,
      "scopedVars": {
        "host": {
          "selected": false,
          "text": "ubuntu-vm-test",
          "value": "ubuntu-vm-test"
        }
      },
      "seriesOverrides": [],
      "spaceLength": 10,
      "stack": false,
      "steppedLine": false,
      "targets": [
        {
          "groupBy": [
            {
              "params": [
                "$__interval"
              ],
              "type": "time"
            },
            {
              "params": [
                "null"
              ],
              "type": "fill"
            }
          ],
          "orderByTime": "ASC",
          "policy": "default",
          "query": "SELECT mean(*) FROM \"system\" WHERE (\"host\" =~ /$host/) AND $timeFilter GROUP BY time($__interval) fill(linear)",
          "rawQuery": true,
          "refId": "A",
          "resultFormat": "time_series",
          "select": [
            [
              {
                "params": [
                  "value"
                ],
                "type": "field"
              },
              {
                "params": [],
                "type": "mean"
              }
            ]
          ],
          "tags": []
        }
      ],
      "thresholds": [],
      "timeFrom": null,
      "timeRegions": [],
      "timeShift": null,
      "title": "System - [[host]]",
      "tooltip": {
        "shared": true,
        "sort": 2,
        "value_type": "individual"
      },
      "type": "graph",
      "xaxis": {
        "buckets": null,
        "mode": "time",
        "name": null,
        "show": true,
        "values": []
      },
      "yaxes": [
        {
          "format": "short",
          "label": null,
          "logBase": 1,
          "max": null,
          "min": null,
          "show": true
        },
        {
          "format": "short",
          "label": null,
          "logBase": 1,
          "max": null,
          "min": null,
          "show": true
        }
      ],
      "yaxis": {
        "align": false,
        "alignLevel": null
      }
    }
  ],
  "schemaVersion": 22,
  "style": "dark",
  "tags": [
    "telegraf",
    "linux",
    "ubuntu"
  ],
  "templating": {
    "list": [
      {
        "allValue": null,
        "current": {
          "text": "All",
          "value": [
            "$__all"
          ]
        },
        "hide": 0,
        "includeAll": true,
        "label": null,
        "multi": true,
        "name": "host",
        "options": [
          {
            "selected": true,
            "text": "All",
            "value": "$__all"
          },
          {
            "selected": false,
            "text": "ubuntu-server",
            "value": "ubuntu-server"
          },
          {
            "selected": false,
            "text": "ubuntu-vm-test",
            "value": "ubuntu-vm-test"
          }
        ],
        "query": "ubuntu-server, ubuntu-vm-test",
        "skipUrlSync": false,
        "type": "custom"
      },
      {
        "datasource": "InfluxDB",
        "filters": [],
        "hide": 0,
        "label": null,
        "name": "Filters",
        "skipUrlSync": false,
        "type": "adhoc"
      }
    ]
  },
  "time": {
    "from": "now-6h",
    "to": "now"
  },
  "timepicker": {
    "refresh_intervals": [
      "5s",
      "10s",
      "30s",
      "1m",
      "5m",
      "15m",
      "30m",
      "1h",
      "2h",
      "1d"
    ]
  },
  "timezone": "",
  "title": "Telegraf Metrics - Linux",
  "uid": "ftp1S9fWz",
  "version": 36
}